envpos/POS.py
envpos/__init__.py
envpos/wordcloud.py
envpos/files/__init__.py
envpos/files/pretrained_models/pos-albert/config.json
envpos/files/pretrained_models/pos-albert/pytorch_model.bin
envpos/files/pretrained_models/pos-albert/vocab.txt
envpos/models/__init__.py
envpos/models/albert_ner.py
envpos/models/bert_base.py
envpos/models/bert_ner.py
envpos/models/model_base.py
envpos/models/ner_base.py
envpos/visualizers/__init__.py
envpos/visualizers/dependency_visualizer.py
envpos/visualizers/html_ops.py
envpos/visualizers/pos_visualizer.py
envpos/visualizers/visualizer_base.py
envpos-0.82.dist-info/LICENSE
envpos-0.82.dist-info/METADATA
envpos-0.82.dist-info/WHEEL
envpos-0.82.dist-info/top_level.txt
envpos-0.82.dist-info/RECORD
