Metadata-Version: 2.1
Name: envpos
Version: 0.82
Summary: 环境/政策领域文本词性标注、术语、专有名词识别工具
Home-page: https://github.com/celtics1863/envpos
Author: bihuaibin
Author-email: bi.huaibin@foxmail.com
License: UNKNOWN
Platform: UNKNOWN
Requires-Python: >=3.6
License-File: LICENSE
Requires-Dist: huggingface-hub
Requires-Dist: packaging
Requires-Dist: palettable
Requires-Dist: pytorch-crf
Requires-Dist: numpy
Requires-Dist: pandas
Requires-Dist: tqdm
Requires-Dist: wordcloud
